blockchain_metrics/__init__.py
blockchain_metrics/blockchain_data.py
blockchain_metrics/pre_load_functions.py
blockchain_metrics/test.py
blockchain_metrics-0.2.dist-info/METADATA
blockchain_metrics-0.2.dist-info/WHEEL
blockchain_metrics-0.2.dist-info/top_level.txt
blockchain_metrics-0.2.dist-info/RECORD
