Metadata-Version: 2.1
Name: blockchain-metrics
Version: 0.2
Summary: blockchain-metrics data
Home-page: https://github.com/JuaanM0/blockchain-metrics
Author: JuannM0
Author-email: juannmaxwell@gmail.com
License: MIT
Keywords: bitcoin,blockchain,blockchain-metrics,bitcoin data,bitcoin data science
Platform: UNKNOWN
